create_mcp_app/__init__.py
create_mcp_app/cli.py
create_mcp_app/generator.py
create_mcp_app/templates/fastmcp/.gitignore
create_mcp_app/templates/fastmcp/Dockerfile.j2
create_mcp_app/templates/fastmcp/README.md.j2
create_mcp_app/templates/fastmcp/docker-compose.yml.j2
create_mcp_app/templates/fastmcp/requirements.txt.j2
create_mcp_app/templates/fastmcp/setup.py.j2
create_mcp_app-1.0.7.dist-info/licenses/LICENSE
create_mcp_app-1.0.7.dist-info/METADATA
create_mcp_app-1.0.7.dist-info/WHEEL
create_mcp_app-1.0.7.dist-info/entry_points.txt
create_mcp_app-1.0.7.dist-info/top_level.txt
create_mcp_app-1.0.7.dist-info/RECORD
